airo_drake/__init__.py
airo_drake/exceptions.py
airo_drake/scene.py
airo_drake/building/__init__.py
airo_drake/building/finish.py
airo_drake/building/floor.py
airo_drake/building/manipulator.py
airo_drake/building/meshcat.py
airo_drake/building/mobile_platform.py
airo_drake/building/wall.py
airo_drake/collision/__init__.py
airo_drake/collision/collision_checking.py
airo_drake/path/__init__.py
airo_drake/path/analysis.py
airo_drake/path/processing.py
airo_drake/time_parametrization/__init__.py
airo_drake/time_parametrization/toppra.py
airo_drake/trajectory/__init__.py
airo_drake/trajectory/concatenate.py
airo_drake/trajectory/discretize.py
airo_drake/trajectory/interpolate.py
airo_drake/trajectory/timing.py
airo_drake/visualization/__init__.py
airo_drake/visualization/arrow.py
airo_drake/visualization/frame.py
airo_drake/visualization/joints.py
airo_drake/visualization/mobile_platform.py
airo_drake-0.0.8.dist-info/licenses/LICENSE
airo_drake-0.0.8.dist-info/METADATA
airo_drake-0.0.8.dist-info/WHEEL
airo_drake-0.0.8.dist-info/top_level.txt
airo_drake-0.0.8.dist-info/RECORD
