Metadata-Version: 2.4
Name: airo-drake
Version: 0.0.8
Summary: Integration between airo-mono and Drake.
Author-email: Andreas Verleysen <andreas.verleysen@ugent.be>, Victor-Louis De Gusseme <victorlouisdg@gmail.com>, Mathieu De Coster <mathieu.decoster@ugent.be>
Project-URL: Homepage, https://github.com/airo-ugent/airo-drake
Project-URL: Issues, https://github.com/airo-ugent/airo-drake/issues
Classifier: Programming Language :: Python :: 3
Classifier: License :: OSI Approved :: MIT License
Classifier: Operating System :: OS Independent
Requires-Python: >=3.10
License-File: LICENSE
Requires-Dist: airo-models>=0.0.12
Requires-Dist: airo-typing>=2025.11.0
Requires-Dist: drake>=1.47.0
Requires-Dist: loguru>=0.7.3
Requires-Dist: ur-analytic-ik>=0.0.4
Dynamic: license-file
